Workbook
Name SelectedIndustry: #REF!

Sheet Project Overview
B2: Dropshipping Profit Optimization & Analytics System
B5: Project Objective | C5: Analyze dropshipping profitability using generated business data, product performance tracking, scenario analysis, and KPI dashboards to support data-driven business decisions.
B7: How to use
B8: 1 | C8: Review Raw_Data for transaction-level records.
B9: 2 | C9: Explore Product Master for product information.
B10: 3 | C10: Use Profit Calculator to estimate profitability.
B11: 4 | C11: Test business cases in Scenario Analysis.
B12: 5 | C12: Review KPIs in Executive Dashboard.
B17: Tools & Techniques Used | C17: Dataset Summary
B18: Excel Advanced Functions | C18: 500 Generated Transactions
B19: Power Query (ETL) | C19: Multiple Product Categories
B20: Business Intelligence | C20: Marketing Channel Analysis
B21: KPI Dashboarding | C21: Revenue & Profit Tracking
B22: Scenario Analysis
B23: Data Generation

Sheet Raw Data
A1: Order ID | B1: Order Date | C1: Year | D1: Month | E1: Country | F1: City | G1: Channel | H1: Campaign | I1: Product ID | J1: Product | K1: Category | L1: Supplier | M1: Sell Price | N1: Buy Cost | O1: Shipping Cost | P1: Fee % | Q1: Ad Cost | R1: Units | S1: Revenue | T1: Product Cost | U1: Shipping Total | V1: Fees Cost | W1: Refund Flag | X1: Refund Cost | Y1: Total Cost | Z1: Net Profit | AA1: Margin % | AB1: ROAS | AC1: Order Status
A2: ORD-00067 | B2: 45659 | C2: 2025 | D2: 1 | E2: Saudi Arabia | F2: Riyadh | G2: Influencer | H2: New Creative A/B | I2: P010 | J2: Smart Water Bottle | K2: Lifestyle | L2: Shenzhen Smart Home | M2: 36.23 | N2: 10.63 | O2: 3.93 | P2: 0.03 | Q2: 18.35 | R2: 2 | S2: =IF(AC2="Cancelled",0,M2*R2) -> 72.46 | T2: =IF(AC2="Cancelled",0,N2*R2) -> 21.26 | U2: =IF(AC2="Cancelled",0,O2*R2) -> 7.86 | V2: =IF(AC2="Cancelled",0,ROUND(P2*S2,2)) -> 2.17 | W2: No | X2: 0 | Y2: =IF(AC2="Cancelled",0,T2+U2+V2+Q2+X2) -> 49.64 | Z2: =IF(AC2="Cancelled",-Q2,S2-Y2) -> 22.82 | AA2: =IF(OR(AC2="Cancelled",S2=0),0,Z2/S2) -> 0.31493238 | AB2: =IFERROR(S2/Q2,0) -> 3.9487738 | AC2: Delivered
A3: ORD-00475 | B3: 45659 | C3: 2025 | D3: 1 | E3: Oman | F3: Muscat | G3: Organic Search | H3: New Creative A/B | I3: P009 | J3: Car Vacuum Cleaner | K3: Automotive | L3: Dongguan Auto Tools | M3: 46.71 | N3: 13.78 | O3: 6 | P3: 0.03 | Q3: 0 | R3: 3 | S3: =IF(AC3="Cancelled",0,M3*R3) -> 140.13 | T3: =IF(AC3="Cancelled",0,N3*R3) -> 41.34 | U3: =IF(AC3="Cancelled",0,O3*R3) -> 18 | V3: =IF(AC3="Cancelled",0,ROUND(P3*S3,2)) -> 4.2 | W3: No | X3: 0 | Y3: =IF(AC3="Cancelled",0,T3+U3+V3+Q3+X3) -> 63.54 | Z3: =IF(AC3="Cancelled",-Q3,S3-Y3) -> 76.59 | AA3: =IF(OR(AC3="Cancelled",S3=0),0,Z3/S3) -> 0.5465639 | AB3: =IFERROR(S3/Q3,0) -> 0 | AC3: Delivered
A4: ORD-00241 | B4: 45660 | C4: 2025 | D4: 1 | E4: UAE | F4: Dubai | G4: Email | H4: Retargeting | I4: P003 | J4: LED Strip Lights | K4: Home Decor | L4: Yiwu Lighting Factory | M4: 27.16 | N4: 5.99 | O4: 3.73 | P4: 0.03 | Q4: 22.04 | R4: 3 | S4: =IF(AC4="Cancelled",0,M4*R4) -> 81.48 | T4: =IF(AC4="Cancelled",0,N4*R4) -> 17.97 | U4: =IF(AC4="Cancelled",0,O4*R4) -> 11.19 | V4: =IF(AC4="Cancelled",0,ROUND(P4*S4,2)) -> 2.44 | W4: No | X4: 0 | Y4: =IF(AC4="Cancelled",0,T4+U4+V4+Q4+X4) -> 53.64 | Z4: =IF(AC4="Cancelled",-Q4,S4-Y4) -> 27.84 | AA4: =IF(OR(AC4="Cancelled",S4=0),0,Z4/S4) -> 0.34167894 | AB4: =IFERROR(S4/Q4,0) -> 3.6969147 | AC4: Delivered
A5: ORD-00459 | B5: 45660 | C5: 2025 | D5: 1 | E5: Oman | F5: Muscat | G5: Email | H5: Summer Sale | I5: P005 | J5: Mini Printer | K5: Electronics | L5: Shenzhen Print Tech | M5: 65.77 | N5: 21.01 | O5: 7.19 | P5: 0.03 | Q5: 9.62 | R5: 1 | S5: =IF(AC5="Cancelled",0,M5*R5) -> 65.77 | T5: =IF(AC5="Cancelled",0,N5*R5) -> 21.01 | U5: =IF(AC5="Cancelled",0,O5*R5) -> 7.19 | V5: =IF(AC5="Cancelled",0,ROUND(P5*S5,2)) -> 1.97 | W5: No | X5: 0 | Y5: =IF(AC5="Cancelled",0,T5+U5+V5+Q5+X5) -> 39.79 | Z5: =IF(AC5="Cancelled",-Q5,S5-Y5) -> 25.98 | AA5: =IF(OR(AC5="Cancelled",S5=0),0,Z5/S5) -> 0.39501292 | AB5: =IFERROR(S5/Q5,0) -> 6.8367983 | AC5: Delivered
A6: ORD-00054 | B6: 45661 | C6: 2025 | D6: 1 | E6: Saudi Arabia | F6: Jeddah | G6: Google Ads | H6: Retargeting | I6: P009 | J6: Car Vacuum Cleaner | K6: Automotive | L6: Dongguan Auto Tools | M6: 41.33 | N6: 15.02 | O6: 7.07 | P6: 0.03 | Q6: 27.25 | R6: 3 | S6: =IF(AC6="Cancelled",0,M6*R6) -> 123.99 | T6: =IF(AC6="Cancelled",0,N6*R6) -> 45.06 | U6: =IF(AC6="Cancelled",0,O6*R6) -> 21.21 | V6: =IF(AC6="Cancelled",0,ROUND(P6*S6,2)) -> 3.72 | W6: No | X6: 0 | Y6: =IF(AC6="Cancelled",0,T6+U6+V6+Q6+X6) -> 97.24 | Z6: =IF(AC6="Cancelled",-Q6,S6-Y6) -> 26.75 | AA6: =IF(OR(AC6="Cancelled",S6=0),0,Z6/S6) -> 0.21574321 | AB6: =IFERROR(S6/Q6,0) -> 4.5500917 | AC6: Delivered
A7: ORD-00386 | B7: 45661 | C7: 2025 | D7: 1 | E7: Qatar | F7: Doha | G7: Email | H7: Retargeting | I7: P006 | J7: Posture Corrector | K7: Fitness | L7: Hangzhou Health Gear | M7: 36.04 | N7: 8.56 | O7: 3.75 | P7: 0.03 | Q7: 8.57 | R7: 1 | S7: =IF(AC7="Cancelled",0,M7*R7) -> 36.04 | T7: =IF(AC7="Cancelled",0,N7*R7) -> 8.56 | U7: =IF(AC7="Cancelled",0,O7*R7) -> 3.75 | V7: =IF(AC7="Cancelled",0,ROUND(P7*S7,2)) -> 1.08 | W7: No | X7: 0 | Y7: =IF(AC7="Cancelled",0,T7+U7+V7+Q7+X7) -> 21.96 | Z7: =IF(AC7="Cancelled",-Q7,S7-Y7) -> 14.08 | AA7: =IF(OR(AC7="Cancelled",S7=0),0,Z7/S7) -> 0.39067703 | AB7: =IFERROR(S7/Q7,0) -> 4.2053676 | AC7: Delivered
A8: ORD-00040 | B8: 45664 | C8: 2025 | D8: 1 | E8: UAE | F8: Abu Dhabi | G8: Email | H8: Summer Sale | I8: P003 | J8: LED Strip Lights | K8: Home Decor | L8: Yiwu Lighting Factory | M8: 26.71 | N8: 6.12 | O8: 3.4 | P8: 0.03 | Q8: 6.87 | R8: 1 | S8: =IF(AC8="Cancelled",0,M8*R8) -> 26.71 | T8: =IF(AC8="Cancelled",0,N8*R8) -> 6.12 | U8: =IF(AC8="Cancelled",0,O8*R8) -> 3.4 | V8: =IF(AC8="Cancelled",0,ROUND(P8*S8,2)) -> 0.8 | W8: No | X8: 0 | Y8: =IF(AC8="Cancelled",0,T8+U8+V8+Q8+X8) -> 17.19 | Z8: =IF(AC8="Cancelled",-Q8,S8-Y8) -> 9.52 | AA8: =IF(OR(AC8="Cancelled",S8=0),0,Z8/S8) -> 0.35642082 | AB8: =IFERROR(S8/Q8,0) -> 3.8879185 | AC8: Delivered
A9: ORD-00203 | B9: 45664 | C9: 2025 | D9: 1 | E9: UAE | F9: Sharjah | G9: TikTok Ads | H9: Summer Sale | I9: P006 | J9: Posture Corrector | K9: Fitness | L9: Hangzhou Health Gear | M9: 33.08 | N9: 9.71 | O9: 3.77 | P9: 0.03 | Q9: 3.96 | R9: 2 | S9: =IF(AC9="Cancelled",0,M9*R9) -> 66.16 | T9: =IF(AC9="Cancelled",0,N9*R9) -> 19.42 | U9: =IF(AC9="Cancelled",0,O9*R9) -> 7.54 | V9: =IF(AC9="Cancelled",0,ROUND(P9*S9,2)) -> 1.98 | W9: No | X9: 0 | Y9: =IF(AC9="Cancelled",0,T9+U9+V9+Q9+X9) -> 32.9 | Z9: =IF(AC9="Cancelled",-Q9,S9-Y9) -> 33.26 | AA9: =IF(OR(AC9="Cancelled",S9=0),0,Z9/S9) -> 0.50272068 | AB9: =IFERROR(S9/Q9,0) -> 16.707071 | AC9: Delivered
A10: ORD-00038 | B10: 45665 | C10: 2025 | D10: 1 | E10: UAE | F10: Sharjah | G10: Google Ads | H10: Summer Sale | I10: P007 | J10: Pet Grooming Glove | K10: Pets | L10: Yiwu Pet Products | M10: 20.42 | N10: 3.35 | O10: 2.49 | P10: 0.03 | Q10: 16.08 | R10: 3 | S10: =IF(AC10="Cancelled",0,M10*R10) -> 61.26 | T10: =IF(AC10="Cancelled",0,N10*R10) -> 10.05 | U10: =IF(AC10="Cancelled",0,O10*R10) -> 7.47 | V10: =IF(AC10="Cancelled",0,ROUND(P10*S10,2)) -> 1.84 | W10: No | X10: 0 | Y10: =IF(AC10="Cancelled",0,T10+U10+V10+Q10+X10) -> 35.44 | Z10: =IF(AC10="Cancelled",-Q10,S10-Y10) -> 25.82 | AA10: =IF(OR(AC10="Cancelled",S10=0),0,Z10/S10) -> 0.42148221 | AB10: =IFERROR(S10/Q10,0) -> 3.8097015 | AC10: Delivered
A11: ORD-00401 | B11: 45666 | C11: 2025 | D11: 1 | E11: UAE | F11: Dubai | G11: Google Ads | H11: Launch Test | I11: P008 | J11: Portable Blender | K11: Kitchen | L11: Foshan Appliances | M11: 53.18 | N11: 16.82 | O11: 5.87 | P11: 0.03 | Q11: 5.9 | R11: 1 | S11: =IF(AC11="Cancelled",0,M11*R11) -> 53.18 | T11: =IF(AC11="Cancelled",0,N11*R11) -> 16.82 | U11: =IF(AC11="Cancelled",0,O11*R11) -> 5.87 | V11: =IF(AC11="Cancelled",0,ROUND(P11*S11,2)) -> 1.6 | W11: No | X11: 0 | Y11: =IF(AC11="Cancelled",0,T11+U11+V11+Q11+X11) -> 30.19 | Z11: =IF(AC11="Cancelled",-Q11,S11-Y11) -> 22.99 | AA11: =IF(OR(AC11="Cancelled",S11=0),0,Z11/S11) -> 0.43230538 | AB11: =IFERROR(S11/Q11,0) -> 9.0135593 | AC11: Delivered
A12: ORD-00451 | B12: 45667 | C12: 2025 | D12: 1 | E12: UAE | F12: Dubai | G12: TikTok Ads | H12: Launch Test | I12: P003 | J12: LED Strip Lights | K12: Home Decor | L12: Yiwu Lighting Factory | M12: 24.36 | N12: 6.05 | O12: 3.32 | P12: 0.03 | Q12: 3.24 | R12: 1 | S12: =IF(AC12="Cancelled",0,M12*R12) -> 24.36 | T12: =IF(AC12="Cancelled",0,N12*R12) -> 6.05 | U12: =IF(AC12="Cancelled",0,O12*R12) -> 3.32 | V12: =IF(AC12="Cancelled",0,ROUND(P12*S12,2)) -> 0.73 | W12: No | X12: 0 | Y12: =IF(AC12="Cancelled",0,T12+U12+V12+Q12+X12) -> 13.34 | Z12: =IF(AC12="Cancelled",-Q12,S12-Y12) -> 11.02 | AA12: =IF(OR(AC12="Cancelled",S12=0),0,Z12/S12) -> 0.45238095 | AB12: =IFERROR(S12/Q12,0) -> 7.5185185 | AC12: Delivered
A13: ORD-00309 | B13: 45668 | C13: 2025 | D13: 1 | E13: Oman | F13: Muscat | G13: TikTok Ads | H13: Launch Test | I13: P009 | J13: Car Vacuum Cleaner | K13: Automotive | L13: Dongguan Auto Tools | M13: 45.62 | N13: 13.94 | O13: 7.25 | P13: 0.03 | Q13: 4.62 | R13: 2 | S13: =IF(AC13="Cancelled",0,M13*R13) -> 91.24 | T13: =IF(AC13="Cancelled",0,N13*R13) -> 27.88 | U13: =IF(AC13="Cancelled",0,O13*R13) -> 14.5 | V13: =IF(AC13="Cancelled",0,ROUND(P13*S13,2)) -> 2.74 | W13: No | X13: 0 | Y13: =IF(AC13="Cancelled",0,T13+U13+V13+Q13+X13) -> 49.74 | Z13: =IF(AC13="Cancelled",-Q13,S13-Y13) -> 41.5 | AA13: =IF(OR(AC13="Cancelled",S13=0),0,Z13/S13) -> 0.45484437 | AB13: =IFERROR(S13/Q13,0) -> 19.748918 | AC13: Delivered
... A501: ORD-00448 | B501: 46141 | C501: 2026 | D501: 4 | E501: Saudi Arabia | F501: Jeddah | G501: Google Ads | H501: Retargeting | I501: P004 | J501: Beauty Tool | K501: Beauty | L501: Ningbo Beauty Supply | M501: 30.3 | N501: 6.84 | O501: 4.26 | P501: 0.03 | Q501: 7.6 | R501: 2 | S501: =IF(AC501="Cancelled",0,M501*R501) -> 0 | T501: =IF(AC501="Cancelled",0,N501*R501) -> 0 | U501: =IF(AC501="Cancelled",0,O501*R501) -> 0 | V501: =IF(AC501="Cancelled",0,ROUND(P501*S501,2)) -> 0 | W501: No | X501: 0 | Y501: =IF(AC501="Cancelled",0,T501+U501+V501+Q501+X501) -> 0 | Z501: =IF(AC501="Cancelled",-Q501,S501-Y501) -> -7.6 | AA501: =IF(OR(AC501="Cancelled",S501=0),0,Z501/S501) -> 0 | AB501: =IFERROR(S501/Q501,0) -> 0 | AC501: Cancelled

Sheet Product Master
A1: Product ID | B1: Product | C1: Category | D1: Supplier | E1: Sell Price | F1: Buy Cost | G1: Shipping Cost | H1: Fee % | I1: Profit per Unit | J1: Margin %
A2: P001 | B2: Wireless Earbuds | C2: Electronics | D2: Shenzhen Audio Co. | E2: 39.99 | F2: 8.5 | G2: 4 | H2: 0.03 | I2: =E2-F2-G2-(E2*H2) -> 26.2903 | J2: =I2/E2 -> 0.65742186
A3: P002 | B3: Phone Case | C3: Accessories | D3: Guangzhou Cases Ltd. | E3: 14.99 | F3: 2 | G3: 2 | H3: 0.03 | I3: =E3-F3-G3-(E3*H3) -> 10.5403 | J3: =I3/E3 -> 0.70315544
A4: P003 | B4: LED Strip Lights | C4: Home Decor | D4: Yiwu Lighting Factory | E4: 24.99 | F4: 6 | G4: 3.5 | H4: 0.03 | I4: =E4-F4-G4-(E4*H4) -> 14.7403 | J4: =I4/E4 -> 0.58984794
A5: P004 | B5: Beauty Tool | C5: Beauty | D5: Ningbo Beauty Supply | E5: 29.99 | F5: 7 | G5: 4.5 | H5: 0.03 | I5: =E5-F5-G5-(E5*H5) -> 17.5903 | J5: =I5/E5 -> 0.58653885
A6: P005 | B6: Mini Printer | C6: Electronics | D6: Shenzhen Print Tech | E6: 59.99 | F6: 22 | G6: 7 | H6: 0.03 | I6: =E6-F6-G6-(E6*H6) -> 29.1903 | J6: =I6/E6 -> 0.4865861
A7: P006 | B7: Posture Corrector | C7: Fitness | D7: Hangzhou Health Gear | E7: 34.99 | F7: 9 | G7: 4 | H7: 0.03 | I7: =E7-F7-G7-(E7*H7) -> 20.9403 | J7: =I7/E7 -> 0.59846528
A8: P007 | B8: Pet Grooming Glove | C8: Pets | D8: Yiwu Pet Products | E8: 19.99 | F8: 3.5 | G8: 2.5 | H8: 0.03 | I8: =E8-F8-G8-(E8*H8) -> 13.3903 | J8: =I8/E8 -> 0.66984992
A9: P008 | B9: Portable Blender | C9: Kitchen | D9: Foshan Appliances | E9: 49.99 | F9: 16 | G9: 6 | H9: 0.03 | I9: =E9-F9-G9-(E9*H9) -> 26.4903 | J9: =I9/E9 -> 0.52991198
A10: P009 | B10: Car Vacuum Cleaner | C10: Automotive | D10: Dongguan Auto Tools | E10: 44.99 | F10: 14 | G10: 6.5 | H10: 0.03 | I10: =E10-F10-G10-(E10*H10) -> 23.1403 | J10: =I10/E10 -> 0.51434319
A11: P010 | B11: Smart Water Bottle | C11: Lifestyle | D11: Shenzhen Smart Home | E11: 32.99 | F11: 10 | G11: 4 | H11: 0.03 | I11: =E11-F11-G11-(E11*H11) -> 18.0003 | J11: =I11/E11 -> 0.54562898

Sheet Profit Calculator
B2: =IF(SelectedIndustry="SaaS","SaaS Profitability & Marketing Analysis Model",IF(SelectedIndustry="Retail","Retail Profitability & Marketing Analysis Model","Dropshipping Profitability & Marketing Analysis Model")) -> #REF!
B4: Blue cells = inputs | Black cells = formulas | Designed for beginners and product testing
B6: Revenue Inputs | G6: Decision Engine
B7: =IF(SelectedIndustry="SaaS","MRR per Customer ($)",IF(SelectedIndustry="Retail","Retail Price per Unit ($)","Selling Price per Unit ($)")) -> #REF! | C7: 49.99 | D7: Primary price customers pay | G7: Profitability Score | H7: =MIN(100,MAX(0,(C27/0.3)*100)) -> 100
B8: =IF(SelectedIndustry="SaaS","Customers (MRR)",IF(SelectedIndustry="Retail","Units Sold per Month","Units Sold per Month")) -> #REF! | C8: 100 | D8: Expected monthly unit sales | G8: ROAS Score | H8: =MIN(100,MAX(0,(C34/C40)*50)) -> 100
B9: Organic Sales % | C9: 0.2 | D9: Share of units not from paid ads | G9: Margin Score | H9: =MIN(100,MAX(0,(C25/0.55)*100)) -> 99.985452
B10: =IF(SelectedIndustry="SaaS","MRR ($)",IF(SelectedIndustry="Retail","Gross Sales ($)","Total Revenue ($)")) -> #REF! | C10: =C7*C8 -> 4999 | G10: Risk Score | H10: =MAX(0,100-(C19*300)-(IF(C36<3,30,0))) -> 94
B11: Revenue from Paid Ads ($) | C11: =C10*(1-C9) -> 3999.2 | G11: Winning Score /100 | H11: =ROUND(AVERAGE(H7:H10),0) -> 98
G12: Product Verdict | H12: =IF(C26<=0,"❌ Avoid Product",IF(H11>=80,"✅ Test / Scale",IF(H11>=60,"⚠️ Optimize First","❌ Avoid / Rework"))) -> ✅ Test / Scale
B13: Costs & Fees | G13: Ad Safety Status | H13: =IF(C34>=C40,"✅ Above break-even","⚠️ Below break-even") -> ✅ Above break-even
B14: =IF(SelectedIndustry="SaaS","Cost to Serve per Unit ($)",IF(SelectedIndustry="Retail","COGS per Unit ($)","Product Cost per Unit ($)")) -> #REF! | C14: 15
B15: =IF(SelectedIndustry="SaaS","Infrastructure Cost per Unit ($)",IF(SelectedIndustry="Retail","Fulfillment Cost per Unit ($)","Shipping Cost per Unit ($)")) -> #REF! | C15: 5 | G15: Business note
B16: Platform / Payment Fee % | C16: 0.03 | G16: Break-even ROAS is based on contribution margin before ads, so it is more accurate than total revenue/ad spend.
B17: =IF(SelectedIndustry="SaaS","Growth Spend ($)",IF(SelectedIndustry="Retail","Marketing Spend ($)","Ad Spend ($)")) -> #REF! | C17: 300
B18: Other Fixed Expenses ($) | C18: 50
B19: =IF(SelectedIndustry="SaaS","Churn Rate %",IF(SelectedIndustry="Retail","Return Rate %","Refund / Return Rate %")) -> #REF! | C19: 0.02
B20: =IF(SelectedIndustry="SaaS","Churn Revenue Loss ($)",IF(SelectedIndustry="Retail","Return Handling Cost ($)","Refund Cost Estimate ($)")) -> #REF! | C20: =C10*C19 -> 99.98
B21: Total Costs ($) | C21: =((C14+C15)*C8)+(C16*C10)+C17+C18+C20 -> 2599.95
B23: Unit Economics
B24: =IF(SelectedIndustry="SaaS","Gross Margin Before Growth Spend ($)",IF(SelectedIndustry="Retail","Gross Profit Before Ads ($)","Contribution Margin Before Ads ($)")) -> #REF! | C24: =C7-C14-C15-(C16*C7)-(C19*C7) -> 27.4905
B25: Contribution Margin % | C25: =IF(C7=0,0,C24/C7) -> 0.54991998
B26: Net Profit ($) | C26: =C10-C21 -> 2399.05
B27: Net Profit Margin | C27: =IF(C10=0,0,C26/C10) -> 0.47990598
B28: Profit per Unit ($) | C28: =IF(C8=0,0,C26/C8) -> 23.9905
B30: Marketing KPIs
B31: New Customers Acquired | C31: 40
B32: Average Order Value / AOV ($) | C32: =C7 -> 49.99
B33: =IF(SelectedIndustry="SaaS","LTV / MRR Ratio ($)",IF(SelectedIndustry="Retail","Customer Lifetime Value / LTV ($)","Customer Lifetime Value / LTV ($)")) -> #REF! | C33: =C7*3 -> 149.97
B34: =IF(SelectedIndustry="SaaS","CAC Payback Ratio",IF(SelectedIndustry="Retail","ROAS from Paid Ads","ROAS from Paid Ads")) -> #REF! | C34: =IF(C17=0,0,C11/C17) -> 13.330667
B35: CAC ($) | C35: =IF(C31=0,0,C17/C31) -> 7.5
B36: LTV:CAC Ratio | C36: =IF(C35=0,0,C33/C35) -> 19.996
B38: Break-even Logic
B39: Max Ad Cost per Unit at Break-even ($) | C39: =MAX(0,C24) -> 27.4905
B40: Break-even ROAS (Paid Ads Only) | C40: =IF(C24<=0,"N/A",C7/C24) -> 1.8184464
B41: Break-even CPA / CAC ($) | C41: =MAX(0,C24) -> 27.4905
B42: Break-even Units | C42: =IF(C24<=0,"N/A",CEILING((C17+C18)/C24,1)) -> 13
B43: Break-even Revenue ($) | C43: =IF(ISNUMBER(C42),C42*C7,"N/A") -> 649.87

Sheet Scenario Analysis
B2: Business Scenario Analysis
B5: Metric | C5: Base Case | D5: Scenario A | E5: Scenario B | F5: Scenario C
B6: Selling Price ($) | C6: ='Profit Calculator'!C7 -> 49.99 | D6: 49.99 | E6: 49.99 | F6: 49.99
B7: Product Cost ($) | C7: ='Profit Calculator'!C14 -> 15 | D7: 15 | E7: 15 | F7: 16
B8: Shipping ($) | C8: ='Profit Calculator'!C15 -> 5 | D8: 5 | E8: 6 | F8: 6
B9: Fee % | C9: ='Profit Calculator'!C16 -> 0.03 | D9: 0.03 | E9: 0.03 | F9: 0.035
B10: Ad Spend ($) | C10: ='Profit Calculator'!C17 -> 300 | D10: 300 | E10: 500 | F10: 800
B11: Units Sold | C11: ='Profit Calculator'!C8 -> 100 | D11: 100 | E11: 150 | F11: 220
B12: Organic Sales % | C12: ='Profit Calculator'!C9 -> 0.2 | D12: 0.2 | E12: 0.15 | F12: 0.1
B13: Revenue ($) | C13: =C6*C11 -> 4999 | D13: =D6*D11 -> 4999 | E13: =E6*E11 -> 7498.5 | F13: =F6*F11 -> 10997.8
B14: Paid Ads Revenue ($) | C14: =C13*(1-C12) -> 3999.2 | D14: =D13*(1-D12) -> 3999.2 | E14: =E13*(1-E12) -> 6373.725 | F14: =F13*(1-F12) -> 9898.02
B15: Contribution Margin ($) | C15: =C6-C7-C8-(C9*C6) -> 28.4903 | D15: =D6-D7-D8-(D9*D6) -> 28.4903 | E15: =E6-E7-E8-(E9*E6) -> 27.4903 | F15: =F6-F7-F8-(F9*F6) -> 26.24035
B16: Total Costs ($) | C16: =((C7+C8)*C11)+(C9*C13)+C10 -> 2449.97 | D16: =((D7+D8)*D11)+(D9*D13)+D10 -> 2449.97 | E16: =((E7+E8)*E11)+(E9*E13)+E10 -> 3874.955 | F16: =((F7+F8)*F11)+(F9*F13)+F10 -> 6024.923
B17: Net Profit ($) | C17: =C13-C16 -> 2549.03 | D17: =D13-D16 -> 2549.03 | E17: =E13-E16 -> 3623.545 | F17: =F13-F16 -> 4972.877
B18: Profit Margin | C18: =IF(C13=0,0,C17/C13) -> 0.50990798 | D18: =IF(D13=0,0,D17/D13) -> 0.50990798 | E18: =IF(E13=0,0,E17/E13) -> 0.48323598 | F18: =IF(F13=0,0,F17/F13) -> 0.45217016
B19: ROAS | C19: =IF(C10=0,0,C14/C10) -> 13.330667 | D19: =IF(D10=0,0,D14/D10) -> 13.330667 | E19: =IF(E10=0,0,E14/E10) -> 12.74745 | F19: =IF(F10=0,0,F14/F10) -> 12.372525
B20: Break-even ROAS | C20: =IF(C15<=0,"N/A",C6/C15) -> 1.7546323 | D20: =IF(D15<=0,"N/A",D6/D15) -> 1.7546323 | E20: =IF(E15<=0,"N/A",E6/E15) -> 1.8184596 | F20: =IF(F15<=0,"N/A",F6/F15) -> 1.9050813
B21: Decision | C21: =IF(C17>0,IF(C19>=C20,"Good","Risky")," Loss") -> Good | D21: =IF(D17>0,IF(D19>=D20,"Good","Risky"),"Loss") -> Good | E21: =IF(E17>0,IF(E19>=E20,"Good","Risky"),"Loss") -> Good | F21: =IF(F17>0,IF(F19>=F20,"Good","Risky"),"Loss") -> Good

Sheet Executive Dashboard
B2: Dashboard — Live Product Profitability
B5: Revenue | D5: Net Profit | F5: ROAS | H5: Score
B6: ='Profit Calculator'!C10 -> 4999 | D6: ='Profit Calculator'!C26 -> 2399.05 | F6: ='Profit Calculator'!C34 -> 13.330667 | H6: ='Profit Calculator'!H11 -> 98
B9: Executive Summary
B10: Product Verdict | C10: ='Profit Calculator'!H12 -> ✅ Test / Scale
B11: Ad Safety | C11: ='Profit Calculator'!H13 -> ✅ Above break-even
B12: Break-even ROAS | C12: ='Profit Calculator'!C40 -> 1.8184464
B13: Break-even CAC | C13: ='Profit Calculator'!C41 -> 27.4905
B14: Profit Margin | C14: ='Profit Calculator'!C27 -> 0.47990598
B15: LTV:CAC | C15: ='Profit Calculator'!C36 -> 19.996
B18: Metric | C18: Value
B19: Revenue | C19: ='Profit Calculator'!C10 -> 4999
B20: Total Costs | C20: ='Profit Calculator'!C21 -> 2599.95
B21: Net Profit | C21: ='Profit Calculator'!C26 -> 2399.05
B22: Ad Spend | C22: ='Profit Calculator'!C17 -> 300

Sheet sales_data_cleaned
A1: Category | B1: Supplier | C1: Sell Price | D1: Buy Cost | E1: Shipping Cost | F1: Fee % | G1: Ad Cost | H1: Units | I1: Revenue | J1: Product Cost | K1: Shipping Total | L1: Fees Cost | M1: Refund Flag | N1: Refund Cost | O1: Total Cost | P1: Net Profit | Q1: Margin % | R1: ROAS | S1: Order Status
A2: Lifestyle | B2: Shenzhen Smart Home | C2: 36.23 | D2: 10.63 | E2: 3.93 | F2: 0.03 | G2: 18.35 | H2: 2 | I2: 72.46 | J2: 21.26 | K2: 7.86 | L2: 2.17 | M2: No | N2: 0 | O2: 49.64 | P2: 22.82 | Q2: 0.315 | R2: 3.95 | S2: Delivered
A3: Automotive | B3: Dongguan Auto Tools | C3: 46.71 | D3: 13.78 | E3: 6 | F3: 0.03 | G3: 0 | H3: 3 | I3: 140.13 | J3: 41.34 | K3: 18 | L3: 4.2 | M3: No | N3: 0 | O3: 63.54 | P3: 76.59 | Q3: 0.547 | R3: 0 | S3: Delivered
A4: Home Decor | B4: Yiwu Lighting Factory | C4: 27.16 | D4: 5.99 | E4: 3.73 | F4: 0.03 | G4: 22.04 | H4: 3 | I4: 81.48 | J4: 17.97 | K4: 11.19 | L4: 2.44 | M4: No | N4: 0 | O4: 53.64 | P4: 27.84 | Q4: 0.342 | R4: 3.7 | S4: Delivered
A5: Electronics | B5: Shenzhen Print Tech | C5: 65.77 | D5: 21.01 | E5: 7.19 | F5: 0.03 | G5: 9.62 | H5: 1 | I5: 65.77 | J5: 21.01 | K5: 7.19 | L5: 1.97 | M5: No | N5: 0 | O5: 39.79 | P5: 25.98 | Q5: 0.395 | R5: 6.84 | S5: Delivered
A6: Automotive | B6: Dongguan Auto Tools | C6: 41.33 | D6: 15.02 | E6: 7.07 | F6: 0.03 | G6: 27.25 | H6: 3 | I6: 123.99 | J6: 45.06 | K6: 21.21 | L6: 3.72 | M6: No | N6: 0 | O6: 97.24 | P6: 26.75 | Q6: 0.216 | R6: 4.55 | S6: Delivered
A7: Fitness | B7: Hangzhou Health Gear | C7: 36.04 | D7: 8.56 | E7: 3.75 | F7: 0.03 | G7: 8.57 | H7: 1 | I7: 36.04 | J7: 8.56 | K7: 3.75 | L7: 1.08 | M7: No | N7: 0 | O7: 21.96 | P7: 14.08 | Q7: 0.391 | R7: 4.21 | S7: Delivered
A8: Home Decor | B8: Yiwu Lighting Factory | C8: 26.71 | D8: 6.12 | E8: 3.4 | F8: 0.03 | G8: 6.87 | H8: 1 | I8: 26.71 | J8: 6.12 | K8: 3.4 | L8: 0.8 | M8: No | N8: 0 | O8: 17.19 | P8: 9.52 | Q8: 0.356 | R8: 3.89 | S8: Delivered
A9: Fitness | B9: Hangzhou Health Gear | C9: 33.08 | D9: 9.71 | E9: 3.77 | F9: 0.03 | G9: 3.96 | H9: 2 | I9: 66.16 | J9: 19.42 | K9: 7.54 | L9: 1.98 | M9: No | N9: 0 | O9: 32.9 | P9: 33.26 | Q9: 0.503 | R9: 16.71 | S9: Delivered
A10: Pets | B10: Yiwu Pet Products | C10: 20.42 | D10: 3.35 | E10: 2.49 | F10: 0.03 | G10: 16.08 | H10: 3 | I10: 61.26 | J10: 10.05 | K10: 7.47 | L10: 1.84 | M10: No | N10: 0 | O10: 35.44 | P10: 25.82 | Q10: 0.421 | R10: 3.81 | S10: Delivered
A11: Kitchen | B11: Foshan Appliances | C11: 53.18 | D11: 16.82 | E11: 5.87 | F11: 0.03 | G11: 5.9 | H11: 1 | I11: 53.18 | J11: 16.82 | K11: 5.87 | L11: 1.6 | M11: No | N11: 0 | O11: 30.19 | P11: 22.99 | Q11: 0.432 | R11: 9.01 | S11: Delivered
A12: Home Decor | B12: Yiwu Lighting Factory | C12: 24.36 | D12: 6.05 | E12: 3.32 | F12: 0.03 | G12: 3.24 | H12: 1 | I12: 24.36 | J12: 6.05 | K12: 3.32 | L12: 0.73 | M12: No | N12: 0 | O12: 13.34 | P12: 11.02 | Q12: 0.452 | R12: 7.52 | S12: Delivered
A13: Automotive | B13: Dongguan Auto Tools | C13: 45.62 | D13: 13.94 | E13: 7.25 | F13: 0.03 | G13: 4.62 | H13: 2 | I13: 91.24 | J13: 27.88 | K13: 14.5 | L13: 2.74 | M13: No | N13: 0 | O13: 49.74 | P13: 41.5 | Q13: 0.455 | R13: 19.75 | S13: Delivered
... A501: Beauty | B501: Ningbo Beauty Supply | C501: 30.3 | D501: 6.84 | E501: 4.26 | F501: 0.03 | G501: 7.6 | H501: 2 | I501: 0 | J501: 0 | K501: 0 | L501: 0 | M501: No | N501: 0 | O501: 0 | P501: -7.6 | Q501: 0 | R501: 0 | S501: Cancelled
