Workbook

Sheet Control Panel
B2: ⚙️ Control Panel — Industry Settings
B4: INDUSTRY SELECTOR
B5: Choose your industry below. All labels in the Profit Calculator will update automatically.
B6: Setting | C6: Dropshipping | D6: Retail | E6: SaaS
B10: Selected Industry ▶ | C10: Dropshipping
B14: DYNAMIC LABEL REFERENCE
B15: Profit Calculator Field | C15: Dropshipping | D15: Retail | E15: SaaS
B16: Selling Price per Unit ($) | C16: Selling Price / Unit ($) | D16: Retail Price / Unit ($) | E16: MRR per Customer ($)
B17: Product Cost per Unit ($) | C17: Product Cost / Unit ($) | D17: COGS / Unit ($) | E17: Cost to Serve / Unit ($)
B18: Shipping Cost per Unit ($) | C18: Shipping Cost / Unit ($) | D18: Fulfillment Cost / Unit ($) | E18: Infrastructure Cost ($)
B19: Ad Spend ($) | C19: Ad Spend ($) | D19: Marketing Spend ($) | E19: Growth Spend ($)
B20: Units Sold per Month | C20: Units Sold / Month | D20: Units Sold / Month | E20: Customers (MRR)
B21: Refund / Return Rate % | C21: Refund / Return Rate % | D21: Return Rate % | E21: Churn Rate %
B22: Refund Cost Estimate ($) | C22: Refund Cost Estimate ($) | D22: Return Handling Cost ($) | E22: Churn Revenue Loss ($)
B23: ROAS from Paid Ads | C23: ROAS from Paid Ads | D23: ROAS from Paid Ads | E23: CAC Payback Ratio
B24: Customer Lifetime Value | C24: LTV ($) | D24: LTV ($) | E24: LTV / MRR Ratio
B25: Contribution Margin | C25: Contribution Margin ($) | D25: Gross Profit ($) | E25: Gross Margin ($)
B26: Total Revenue ($) | C26: Total Revenue ($) | D26: Gross Sales ($) | E26: MRR ($)
B29: 💡 Tip: The selected industry drives all label formulas in "Profit Calculator". Change the dropdown above — labels update instantly.

Sheet Project Overview
B2: Dropshipping Profit Optimization & Analytics System
B5: Project Objective | C5: Analyze dropshipping profitability using generated business data, product performance tracking, scenario analysis, and KPI dashboards to support data-driven business decisions.
B7: How to use
B8: 1 | C8: Review Raw_Data for transaction-level records.
B9: 2 | C9: Explore Product Master for product information.
B10: 3 | C10: Use Profit Calculator to estimate profitability.
B11: 4 | C11: Test business cases in Scenario Analysis.
B12: 5 | C12: Review KPIs in Executive Dashboard.
B17: Tools & Techniques Used | C17: Dataset Summary
B18: Excel Advanced Functions | C18: 500 Generated Transactions
B19: Power Query (ETL) | C19: Multiple Product Categories
B20: Business Intelligence | C20: Marketing Channel Analysis
B21: KPI Dashboarding | C21: Revenue & Profit Tracking
B22: Scenario Analysis
B23: Data Generation

Sheet Raw Data
A1: Order ID | B1: Order Date | C1: Year | D1: Month | E1: Country | F1: City | G1: Channel | H1: Campaign | I1: Product ID | J1: Product | K1: Category | L1: Supplier | M1: Sell Price | N1: Buy Cost | O1: Shipping Cost | P1: Fee % | Q1: Ad Cost | R1: Units | S1: Revenue | T1: Product Cost | U1: Shipping Total | V1: Fees Cost | W1: Refund Flag | X1: Refund Cost | Y1: Total Cost | Z1: Net Profit | AA1: Margin % | AB1: ROAS | AC1: Order Status
A2: ORD-00067 | B2: 45659 | C2: 2025 | D2: 1 | E2: Saudi Arabia | F2: Riyadh | G2: Influencer | H2: New Creative A/B | I2: P010 | J2: Smart Water Bottle | K2: Lifestyle | L2: Shenzhen Smart Home | M2: 36.23 | N2: 10.63 | O2: 3.93 | P2: 0.03 | Q2: 18.35 | R2: 2 | S2: =IF(AC2="Cancelled",0,M2*R2) | T2: =IF(AC2="Cancelled",0,N2*R2) | U2: =IF(AC2="Cancelled",0,O2*R2) | V2: =IF(AC2="Cancelled",0,ROUND(P2*S2,2)) | W2: No | X2: 0 | Y2: =IF(AC2="Cancelled",0,T2+U2+V2+Q2+X2) | Z2: =IF(AC2="Cancelled",-Q2,S2-Y2) | AA2: =IF(OR(AC2="Cancelled",S2=0),0,Z2/S2) | AB2: =IFERROR(S2/Q2,0) | AC2: Delivered
A3: ORD-00475 | B3: 45659 | C3: 2025 | D3: 1 | E3: Oman | F3: Muscat | G3: Organic Search | H3: New Creative A/B | I3: P009 | J3: Car Vacuum Cleaner | K3: Automotive | L3: Dongguan Auto Tools | M3: 46.71 | N3: 13.78 | O3: 6 | P3: 0.03 | Q3: 0 | R3: 3 | S3: =IF(AC3="Cancelled",0,M3*R3) | T3: =IF(AC3="Cancelled",0,N3*R3) | U3: =IF(AC3="Cancelled",0,O3*R3) | V3: =IF(AC3="Cancelled",0,ROUND(P3*S3,2)) | W3: No | X3: 0 | Y3: =IF(AC3="Cancelled",0,T3+U3+V3+Q3+X3) | Z3: =IF(AC3="Cancelled",-Q3,S3-Y3) | AA3: =IF(OR(AC3="Cancelled",S3=0),0,Z3/S3) | AB3: =IFERROR(S3/Q3,0) | AC3: Delivered
A4: ORD-00241 | B4: 45660 | C4: 2025 | D4: 1 | E4: UAE | F4: Dubai | G4: Email | H4: Retargeting | I4: P003 | J4: LED Strip Lights | K4: Home Decor | L4: Yiwu Lighting Factory | M4: 27.16 | N4: 5.99 | O4: 3.73 | P4: 0.03 | Q4: 22.04 | R4: 3 | S4: =IF(AC4="Cancelled",0,M4*R4) | T4: =IF(AC4="Cancelled",0,N4*R4) | U4: =IF(AC4="Cancelled",0,O4*R4) | V4: =IF(AC4="Cancelled",0,ROUND(P4*S4,2)) | W4: No | X4: 0 | Y4: =IF(AC4="Cancelled",0,T4+U4+V4+Q4+X4) | Z4: =IF(AC4="Cancelled",-Q4,S4-Y4) | AA4: =IF(OR(AC4="Cancelled",S4=0),0,Z4/S4) | AB4: =IFERROR(S4/Q4,0) | AC4: Delivered
A5: ORD-00459 | B5: 45660 | C5: 2025 | D5: 1 | E5: Oman | F5: Muscat | G5: Email | H5: Summer Sale | I5: P005 | J5: Mini Printer | K5: Electronics | L5: Shenzhen Print Tech | M5: 65.77 | N5: 21.01 | O5: 7.19 | P5: 0.03 | Q5: 9.62 | R5: 1 | S5: =IF(AC5="Cancelled",0,M5*R5) | T5: =IF(AC5="Cancelled",0,N5*R5) | U5: =IF(AC5="Cancelled",0,O5*R5) | V5: =IF(AC5="Cancelled",0,ROUND(P5*S5,2)) | W5: No | X5: 0 | Y5: =IF(AC5="Cancelled",0,T5+U5+V5+Q5+X5) | Z5: =IF(AC5="Cancelled",-Q5,S5-Y5) | AA5: =IF(OR(AC5="Cancelled",S5=0),0,Z5/S5) | AB5: =IFERROR(S5/Q5,0) | AC5: Delivered
A6: ORD-00054 | B6: 45661 | C6: 2025 | D6: 1 | E6: Saudi Arabia | F6: Jeddah | G6: Google Ads | H6: Retargeting | I6: P009 | J6: Car Vacuum Cleaner | K6: Automotive | L6: Dongguan Auto Tools | M6: 41.33 | N6: 15.02 | O6: 7.07 | P6: 0.03 | Q6: 27.25 | R6: 3 | S6: =IF(AC6="Cancelled",0,M6*R6) | T6: =IF(AC6="Cancelled",0,N6*R6) | U6: =IF(AC6="Cancelled",0,O6*R6) | V6: =IF(AC6="Cancelled",0,ROUND(P6*S6,2)) | W6: No | X6: 0 | Y6: =IF(AC6="Cancelled",0,T6+U6+V6+Q6+X6) | Z6: =IF(AC6="Cancelled",-Q6,S6-Y6) | AA6: =IF(OR(AC6="Cancelled",S6=0),0,Z6/S6) | AB6: =IFERROR(S6/Q6,0) | AC6: Delivered
A7: ORD-00386 | B7: 45661 | C7: 2025 | D7: 1 | E7: Qatar | F7: Doha | G7: Email | H7: Retargeting | I7: P006 | J7: Posture Corrector | K7: Fitness | L7: Hangzhou Health Gear | M7: 36.04 | N7: 8.56 | O7: 3.75 | P7: 0.03 | Q7: 8.57 | R7: 1 | S7: =IF(AC7="Cancelled",0,M7*R7) | T7: =IF(AC7="Cancelled",0,N7*R7) | U7: =IF(AC7="Cancelled",0,O7*R7) | V7: =IF(AC7="Cancelled",0,ROUND(P7*S7,2)) | W7: No | X7: 0 | Y7: =IF(AC7="Cancelled",0,T7+U7+V7+Q7+X7) | Z7: =IF(AC7="Cancelled",-Q7,S7-Y7) | AA7: =IF(OR(AC7="Cancelled",S7=0),0,Z7/S7) | AB7: =IFERROR(S7/Q7,0) | AC7: Delivered
A8: ORD-00040 | B8: 45664 | C8: 2025 | D8: 1 | E8: UAE | F8: Abu Dhabi | G8: Email | H8: Summer Sale | I8: P003 | J8: LED Strip Lights | K8: Home Decor | L8: Yiwu Lighting Factory | M8: 26.71 | N8: 6.12 | O8: 3.4 | P8: 0.03 | Q8: 6.87 | R8: 1 | S8: =IF(AC8="Cancelled",0,M8*R8) | T8: =IF(AC8="Cancelled",0,N8*R8) | U8: =IF(AC8="Cancelled",0,O8*R8) | V8: =IF(AC8="Cancelled",0,ROUND(P8*S8,2)) | W8: No | X8: 0 | Y8: =IF(AC8="Cancelled",0,T8+U8+V8+Q8+X8) | Z8: =IF(AC8="Cancelled",-Q8,S8-Y8) | AA8: =IF(OR(AC8="Cancelled",S8=0),0,Z8/S8) | AB8: =IFERROR(S8/Q8,0) | AC8: Delivered
A9: ORD-00203 | B9: 45664 | C9: 2025 | D9: 1 | E9: UAE | F9: Sharjah | G9: TikTok Ads | H9: Summer Sale | I9: P006 | J9: Posture Corrector | K9: Fitness | L9: Hangzhou Health Gear | M9: 33.08 | N9: 9.71 | O9: 3.77 | P9: 0.03 | Q9: 3.96 | R9: 2 | S9: =IF(AC9="Cancelled",0,M9*R9) | T9: =IF(AC9="Cancelled",0,N9*R9) | U9: =IF(AC9="Cancelled",0,O9*R9) | V9: =IF(AC9="Cancelled",0,ROUND(P9*S9,2)) | W9: No | X9: 0 | Y9: =IF(AC9="Cancelled",0,T9+U9+V9+Q9+X9) | Z9: =IF(AC9="Cancelled",-Q9,S9-Y9) | AA9: =IF(OR(AC9="Cancelled",S9=0),0,Z9/S9) | AB9: =IFERROR(S9/Q9,0) | AC9: Delivered
A10: ORD-00038 | B10: 45665 | C10: 2025 | D10: 1 | E10: UAE | F10: Sharjah | G10: Google Ads | H10: Summer Sale | I10: P007 | J10: Pet Grooming Glove | K10: Pets | L10: Yiwu Pet Products | M10: 20.42 | N10: 3.35 | O10: 2.49 | P10: 0.03 | Q10: 16.08 | R10: 3 | S10: =IF(AC10="Cancelled",0,M10*R10) | T10: =IF(AC10="Cancelled",0,N10*R10) | U10: =IF(AC10="Cancelled",0,O10*R10) | V10: =IF(AC10="Cancelled",0,ROUND(P10*S10,2)) | W10: No | X10: 0 | Y10: =IF(AC10="Cancelled",0,T10+U10+V10+Q10+X10) | Z10: =IF(AC10="Cancelled",-Q10,S10-Y10) | AA10: =IF(OR(AC10="Cancelled",S10=0),0,Z10/S10) | AB10: =IFERROR(S10/Q10,0) | AC10: Delivered
A11: ORD-00401 | B11: 45666 | C11: 2025 | D11: 1 | E11: UAE | F11: Dubai | G11: Google Ads | H11: Launch Test | I11: P008 | J11: Portable Blender | K11: Kitchen | L11: Foshan Appliances | M11: 53.18 | N11: 16.82 | O11: 5.87 | P11: 0.03 | Q11: 5.9 | R11: 1 | S11: =IF(AC11="Cancelled",0,M11*R11) | T11: =IF(AC11="Cancelled",0,N11*R11) | U11: =IF(AC11="Cancelled",0,O11*R11) | V11: =IF(AC11="Cancelled",0,ROUND(P11*S11,2)) | W11: No | X11: 0 | Y11: =IF(AC11="Cancelled",0,T11+U11+V11+Q11+X11) | Z11: =IF(AC11="Cancelled",-Q11,S11-Y11) | AA11: =IF(OR(AC11="Cancelled",S11=0),0,Z11/S11) | AB11: =IFERROR(S11/Q11,0) | AC11: Delivered
A12: ORD-00451 | B12: 45667 | C12: 2025 | D12: 1 | E12: UAE | F12: Dubai | G12: TikTok Ads | H12: Launch Test | I12: P003 | J12: LED Strip Lights | K12: Home Decor | L12: Yiwu Lighting Factory | M12: 24.36 | N12: 6.05 | O12: 3.32 | P12: 0.03 | Q12: 3.24 | R12: 1 | S12: =IF(AC12="Cancelled",0,M12*R12) | T12: =IF(AC12="Cancelled",0,N12*R12) | U12: =IF(AC12="Cancelled",0,O12*R12) | V12: =IF(AC12="Cancelled",0,ROUND(P12*S12,2)) | W12: No | X12: 0 | Y12: =IF(AC12="Cancelled",0,T12+U12+V12+Q12+X12) | Z12: =IF(AC12="Cancelled",-Q12,S12-Y12) | AA12: =IF(OR(AC12="Cancelled",S12=0),0,Z12/S12) | AB12: =IFERROR(S12/Q12,0) | AC12: Delivered
A13: ORD-00309 | B13: 45668 | C13: 2025 | D13: 1 | E13: Oman | F13: Muscat | G13: TikTok Ads | H13: Launch Test | I13: P009 | J13: Car Vacuum Cleaner | K13: Automotive | L13: Dongguan Auto Tools | M13: 45.62 | N13: 13.94 | O13: 7.25 | P13: 0.03 | Q13: 4.62 | R13: 2 | S13: =IF(AC13="Cancelled",0,M13*R13) | T13: =IF(AC13="Cancelled",0,N13*R13) | U13: =IF(AC13="Cancelled",0,O13*R13) | V13: =IF(AC13="Cancelled",0,ROUND(P13*S13,2)) | W13: No | X13: 0 | Y13: =IF(AC13="Cancelled",0,T13+U13+V13+Q13+X13) | Z13: =IF(AC13="Cancelled",-Q13,S13-Y13) | AA13: =IF(OR(AC13="Cancelled",S13=0),0,Z13/S13) | AB13: =IFERROR(S13/Q13,0) | AC13: Delivered
... A501: ORD-00448 | B501: 46141 | C501: 2026 | D501: 4 | E501: Saudi Arabia | F501: Jeddah | G501: Google Ads | H501: Retargeting | I501: P004 | J501: Beauty Tool | K501: Beauty | L501: Ningbo Beauty Supply | M501: 30.3 | N501: 6.84 | O501: 4.26 | P501: 0.03 | Q501: 7.6 | R501: 2 | S501: =IF(AC501="Cancelled",0,M501*R501) | T501: =IF(AC501="Cancelled",0,N501*R501) | U501: =IF(AC501="Cancelled",0,O501*R501) | V501: =IF(AC501="Cancelled",0,ROUND(P501*S501,2)) | W501: No | X501: 0 | Y501: =IF(AC501="Cancelled",0,T501+U501+V501+Q501+X501) | Z501: =IF(AC501="Cancelled",-Q501,S501-Y501) | AA501: =IF(OR(AC501="Cancelled",S501=0),0,Z501/S501) | AB501: =IFERROR(S501/Q501,0) | AC501: Cancelled

Sheet Product Master
A1: Product ID | B1: Product | C1: Category | D1: Supplier | E1: Sell Price | F1: Buy Cost | G1: Shipping Cost | H1: Fee % | I1: Profit per Unit | J1: Margin %
A2: P001 | B2: Wireless Earbuds | C2: Electronics | D2: Shenzhen Audio Co. | E2: 39.99 | F2: 8.5 | G2: 4 | H2: 0.03 | I2: =E2-F2-G2-(E2*H2) | J2: =I2/E2
A3: P002 | B3: Phone Case | C3: Accessories | D3: Guangzhou Cases Ltd. | E3: 14.99 | F3: 2 | G3: 2 | H3: 0.03 | I3: =E3-F3-G3-(E3*H3) | J3: =I3/E3
A4: P003 | B4: LED Strip Lights | C4: Home Decor | D4: Yiwu Lighting Factory | E4: 24.99 | F4: 6 | G4: 3.5 | H4: 0.03 | I4: =E4-F4-G4-(E4*H4) | J4: =I4/E4
A5: P004 | B5: Beauty Tool | C5: Beauty | D5: Ningbo Beauty Supply | E5: 29.99 | F5: 7 | G5: 4.5 | H5: 0.03 | I5: =E5-F5-G5-(E5*H5) | J5: =I5/E5
A6: P005 | B6: Mini Printer | C6: Electronics | D6: Shenzhen Print Tech | E6: 59.99 | F6: 22 | G6: 7 | H6: 0.03 | I6: =E6-F6-G6-(E6*H6) | J6: =I6/E6
A7: P006 | B7: Posture Corrector | C7: Fitness | D7: Hangzhou Health Gear | E7: 34.99 | F7: 9 | G7: 4 | H7: 0.03 | I7: =E7-F7-G7-(E7*H7) | J7: =I7/E7
A8: P007 | B8: Pet Grooming Glove | C8: Pets | D8: Yiwu Pet Products | E8: 19.99 | F8: 3.5 | G8: 2.5 | H8: 0.03 | I8: =E8-F8-G8-(E8*H8) | J8: =I8/E8
A9: P008 | B9: Portable Blender | C9: Kitchen | D9: Foshan Appliances | E9: 49.99 | F9: 16 | G9: 6 | H9: 0.03 | I9: =E9-F9-G9-(E9*H9) | J9: =I9/E9
A10: P009 | B10: Car Vacuum Cleaner | C10: Automotive | D10: Dongguan Auto Tools | E10: 44.99 | F10: 14 | G10: 6.5 | H10: 0.03 | I10: =E10-F10-G10-(E10*H10) | J10: =I10/E10
A11: P010 | B11: Smart Water Bottle | C11: Lifestyle | D11: Shenzhen Smart Home | E11: 32.99 | F11: 10 | G11: 4 | H11: 0.03 | I11: =E11-F11-G11-(E11*H11) | J11: =I11/E11

Sheet Profit Calculator
B2: =IF('Control Panel'!$C$10="SaaS","SaaS Profitability & Marketing Analysis Model",IF('Control Panel'!$C$10="Retail","Retail Profitability & Marketing Analysis Model","Dropshipping Profitability & Marketing Analysis Model"))
B4: Blue cells = inputs | Black cells = formulas | Designed for beginners and product testing
B6: Revenue Inputs | G6: Decision Engine
B7: =IF('Control Panel'!$C$10="SaaS","MRR per Customer ($)",IF('Control Panel'!$C$10="Retail","Retail Price per Unit ($)","Selling Price per Unit ($)")) | C7: 49.99 | D7: Primary price customers pay | G7: Profitability Score | H7: =MIN(100,MAX(0,(C27/0.3)*100))
B8: =IF('Control Panel'!$C$10="SaaS","Customers (MRR)",IF('Control Panel'!$C$10="Retail","Units Sold per Month","Units Sold per Month")) | C8: 100 | D8: Expected monthly unit sales | G8: ROAS Score | H8: =MIN(100,MAX(0,(C34/C40)*50))
B9: Organic Sales % | C9: 0.2 | D9: Share of units not from paid ads | G9: Margin Score | H9: =MIN(100,MAX(0,(C25/0.55)*100))
B10: =IF('Control Panel'!$C$10="SaaS","MRR ($)",IF('Control Panel'!$C$10="Retail","Gross Sales ($)","Total Revenue ($)")) | C10: =C7*C8 | G10: Risk Score | H10: =MAX(0,100-(C19*300)-(IF(C36<3,30,0)))
B11: Revenue from Paid Ads ($) | C11: =C10*(1-C9) | G11: Winning Score /100 | H11: =ROUND(AVERAGE(H7:H10),0)
G12: Product Verdict | H12: =IF(C26<=0,"❌ Avoid Product",IF(H11>=80,"✅ Test / Scale",IF(H11>=60,"⚠️ Optimize First","❌ Avoid / Rework")))
B13: Costs & Fees | G13: Ad Safety Status | H13: =IF(C34>=C40,"✅ Above break-even","⚠️ Below break-even")
B14: =IF('Control Panel'!$C$10="SaaS","Cost to Serve per Unit ($)",IF('Control Panel'!$C$10="Retail","COGS per Unit ($)","Product Cost per Unit ($)")) | C14: 15
B15: =IF('Control Panel'!$C$10="SaaS","Infrastructure Cost per Unit ($)",IF('Control Panel'!$C$10="Retail","Fulfillment Cost per Unit ($)","Shipping Cost per Unit ($)")) | C15: 5 | G15: Business note
B16: Platform / Payment Fee % | C16: 0.03 | G16: Break-even ROAS is based on contribution margin before ads, so it is more accurate than total revenue/ad spend.
B17: =IF('Control Panel'!$C$10="SaaS","Growth Spend ($)",IF('Control Panel'!$C$10="Retail","Marketing Spend ($)","Ad Spend ($)")) | C17: 300
B18: Other Fixed Expenses ($) | C18: 50
B19: =IF('Control Panel'!$C$10="SaaS","Churn Rate %",IF('Control Panel'!$C$10="Retail","Return Rate %","Refund / Return Rate %")) | C19: 0.02
B20: =IF('Control Panel'!$C$10="SaaS","Churn Revenue Loss ($)",IF('Control Panel'!$C$10="Retail","Return Handling Cost ($)","Refund Cost Estimate ($)")) | C20: =C10*C19
B21: Total Costs ($) | C21: =((C14+C15)*C8)+(C16*C10)+C17+C18+C20
B23: Unit Economics
B24: =IF('Control Panel'!$C$10="SaaS","Gross Margin Before Growth Spend ($)",IF('Control Panel'!$C$10="Retail","Gross Profit Before Ads ($)","Contribution Margin Before Ads ($)")) | C24: =C7-C14-C15-(C16*C7)-(C19*C7)
B25: Contribution Margin % | C25: =IF(C7=0,0,C24/C7)
B26: Net Profit ($) | C26: =C10-C21
B27: Net Profit Margin | C27: =IF(C10=0,0,C26/C10)
B28: Profit per Unit ($) | C28: =IF(C8=0,0,C26/C8)
B30: Marketing KPIs
B31: New Customers Acquired | C31: 40
B32: Average Order Value / AOV ($) | C32: =C7
B33: =IF('Control Panel'!$C$10="SaaS","LTV / MRR Ratio ($)",IF('Control Panel'!$C$10="Retail","Customer Lifetime Value / LTV ($)","Customer Lifetime Value / LTV ($)")) | C33: =C7*3
B34: =IF('Control Panel'!$C$10="SaaS","CAC Payback Ratio",IF('Control Panel'!$C$10="Retail","ROAS from Paid Ads","ROAS from Paid Ads")) | C34: =IF(C17=0,0,C11/C17)
B35: CAC ($) | C35: =IF(C31=0,0,C17/C31)
B36: LTV:CAC Ratio | C36: =IF(C35=0,0,C33/C35)
B38: Break-even Logic
B39: Max Ad Cost per Unit at Break-even ($) | C39: =MAX(0,C24)
B40: Break-even ROAS (Paid Ads Only) | C40: =IF(C24<=0,"N/A",C7/C24)
B41: Break-even CPA / CAC ($) | C41: =MAX(0,C24)
B42: Break-even Units | C42: =IF(C24<=0,"N/A",CEILING((C17+C18)/C24,1))
B43: Break-even Revenue ($) | C43: =IF(ISNUMBER(C42),C42*C7,"N/A")

Sheet Scenario Analysis
B2: Business Scenario Analysis
B5: Metric | C5: Base Case | D5: Scenario A | E5: Scenario B | F5: Scenario C
B6: Selling Price ($) | C6: ='Profit Calculator'!C7 | D6: 49.99 | E6: 49.99 | F6: 49.99
B7: Product Cost ($) | C7: ='Profit Calculator'!C14 | D7: 15 | E7: 15 | F7: 16
B8: Shipping ($) | C8: ='Profit Calculator'!C15 | D8: 5 | E8: 6 | F8: 6
B9: Fee % | C9: ='Profit Calculator'!C16 | D9: 0.03 | E9: 0.03 | F9: 0.035
B10: Ad Spend ($) | C10: ='Profit Calculator'!C17 | D10: 300 | E10: 500 | F10: 800
B11: Units Sold | C11: ='Profit Calculator'!C8 | D11: 100 | E11: 150 | F11: 220
B12: Organic Sales % | C12: ='Profit Calculator'!C9 | D12: 0.2 | E12: 0.15 | F12: 0.1
B13: Revenue ($) | C13: =C6*C11 | D13: =D6*D11 | E13: =E6*E11 | F13: =F6*F11
B14: Paid Ads Revenue ($) | C14: =C13*(1-C12) | D14: =D13*(1-D12) | E14: =E13*(1-E12) | F14: =F13*(1-F12)
B15: Contribution Margin ($) | C15: =C6-C7-C8-(C9*C6) | D15: =D6-D7-D8-(D9*D6) | E15: =E6-E7-E8-(E9*E6) | F15: =F6-F7-F8-(F9*F6)
B16: Total Costs ($) | C16: =((C7+C8)*C11)+(C9*C13)+C10 | D16: =((D7+D8)*D11)+(D9*D13)+D10 | E16: =((E7+E8)*E11)+(E9*E13)+E10 | F16: =((F7+F8)*F11)+(F9*F13)+F10
B17: Net Profit ($) | C17: =C13-C16 | D17: =D13-D16 | E17: =E13-E16 | F17: =F13-F16
B18: Profit Margin | C18: =IF(C13=0,0,C17/C13) | D18: =IF(D13=0,0,D17/D13) | E18: =IF(E13=0,0,E17/E13) | F18: =IF(F13=0,0,F17/F13)
B19: ROAS | C19: =IF(C10=0,0,C14/C10) | D19: =IF(D10=0,0,D14/D10) | E19: =IF(E10=0,0,E14/E10) | F19: =IF(F10=0,0,F14/F10)
B20: Break-even ROAS | C20: =IF(C15<=0,"N/A",C6/C15) | D20: =IF(D15<=0,"N/A",D6/D15) | E20: =IF(E15<=0,"N/A",E6/E15) | F20: =IF(F15<=0,"N/A",F6/F15)
B21: Decision | C21: =IF(C17>0,IF(C19>=C20,"Good","Risky")," Loss") | D21: =IF(D17>0,IF(D19>=D20,"Good","Risky"),"Loss") | E21: =IF(E17>0,IF(E19>=E20,"Good","Risky"),"Loss") | F21: =IF(F17>0,IF(F19>=F20,"Good","Risky"),"Loss")

Sheet Data Transformation
A1: Order ID | B1: Order Date | C1: Year | D1: Month | E1: Country | F1: City | G1: Channel | H1: Campaign | I1: Product ID | J1: Product | K1: Category | L1: Supplier | M1: Sell Price | N1: Buy Cost | O1: Shipping Cost | P1: Fee % | Q1: Advertising Cost | R1: Units | S1: Revenue | T1: Product Cost | U1: Shipping Total | V1: Fees Cost | W1: Refund Flag | X1: Refund Cost | Y1: Total Cost | Z1: Net Profit | AA1: Margin % | AB1: ROAS | AC1: Order Status | AD1: Profit Tier | AE1: Month Name
A2: ORD-00067 | B2: 45659 | C2: 2025 | D2: 1 | E2: Saudi Arabia | F2: Riyadh | G2: Influencer | H2: New Creative A/B | I2: P010 | J2: Smart Water Bottle | K2: Lifestyle | L2: Shenzhen Smart Home | M2: 36.23 | N2: 10.63 | O2: 3.93 | P2: 0.03 | Q2: 18.35 | R2: 2 | S2: =IF(AC2="Cancelled",0,M2*R2) | T2: =IF(AC2="Cancelled",0,N2*R2) | U2: =IF(AC2="Cancelled",0,O2*R2) | V2: =IF(AC2="Cancelled",0,ROUND(P2*S2,2)) | W2: No | X2: 0 | Y2: =IF(AC2="Cancelled",0,T2+U2+V2+Q2+X2) | Z2: =IF(AC2="Cancelled",-Q2,S2-Y2) | AA2: =IF(OR(AC2="Cancelled",S2=0),0,Z2/S2) | AB2: =IFERROR(IF(Q2=0,0,S2/Q2),0) | AC2: Delivered | AD2: =IF(Z2<=0,"Low Profit",IF(Z2>=50,"HighProfit","Medium Profit")) | AE2: =TEXT(B2,"mmmm")
A3: ORD-00475 | B3: 45659 | C3: 2025 | D3: 1 | E3: Oman | F3: Muscat | G3: Organic Search | H3: New Creative A/B | I3: P009 | J3: Car Vacuum Cleaner | K3: Automotive | L3: Dongguan Auto Tools | M3: 46.71 | N3: 13.78 | O3: 6 | P3: 0.03 | Q3: 0 | R3: 3 | S3: =IF(AC3="Cancelled",0,M3*R3) | T3: =IF(AC3="Cancelled",0,N3*R3) | U3: =IF(AC3="Cancelled",0,O3*R3) | V3: =IF(AC3="Cancelled",0,ROUND(P3*S3,2)) | W3: No | X3: 0 | Y3: =IF(AC3="Cancelled",0,T3+U3+V3+Q3+X3) | Z3: =IF(AC3="Cancelled",-Q3,S3-Y3) | AA3: =IF(OR(AC3="Cancelled",S3=0),0,Z3/S3) | AB3: =IFERROR(IF(Q3=0,0,S3/Q3),0) | AC3: Delivered | AD3: =IF(Z3<=0,"Low Profit",IF(Z3>=50,"HighProfit","Medium Profit")) | AE3: =TEXT(B3,"mmmm")
A4: ORD-00241 | B4: 45660 | C4: 2025 | D4: 1 | E4: UAE | F4: Dubai | G4: Email | H4: Retargeting | I4: P003 | J4: LED Strip Lights | K4: Home Decor | L4: Yiwu Lighting Factory | M4: 27.16 | N4: 5.99 | O4: 3.73 | P4: 0.03 | Q4: 22.04 | R4: 3 | S4: =IF(AC4="Cancelled",0,M4*R4) | T4: =IF(AC4="Cancelled",0,N4*R4) | U4: =IF(AC4="Cancelled",0,O4*R4) | V4: =IF(AC4="Cancelled",0,ROUND(P4*S4,2)) | W4: No | X4: 0 | Y4: =IF(AC4="Cancelled",0,T4+U4+V4+Q4+X4) | Z4: =IF(AC4="Cancelled",-Q4,S4-Y4) | AA4: =IF(OR(AC4="Cancelled",S4=0),0,Z4/S4) | AB4: =IFERROR(IF(Q4=0,0,S4/Q4),0) | AC4: Delivered | AD4: =IF(Z4<=0,"Low Profit",IF(Z4>=50,"HighProfit","Medium Profit")) | AE4: =TEXT(B4,"mmmm")
A5: ORD-00459 | B5: 45660 | C5: 2025 | D5: 1 | E5: Oman | F5: Muscat | G5: Email | H5: Summer Sale | I5: P005 | J5: Mini Printer | K5: Electronics | L5: Shenzhen Print Tech | M5: 65.77 | N5: 21.01 | O5: 7.19 | P5: 0.03 | Q5: 9.62 | R5: 1 | S5: =IF(AC5="Cancelled",0,M5*R5) | T5: =IF(AC5="Cancelled",0,N5*R5) | U5: =IF(AC5="Cancelled",0,O5*R5) | V5: =IF(AC5="Cancelled",0,ROUND(P5*S5,2)) | W5: No | X5: 0 | Y5: =IF(AC5="Cancelled",0,T5+U5+V5+Q5+X5) | Z5: =IF(AC5="Cancelled",-Q5,S5-Y5) | AA5: =IF(OR(AC5="Cancelled",S5=0),0,Z5/S5) | AB5: =IFERROR(IF(Q5=0,0,S5/Q5),0) | AC5: Delivered | AD5: =IF(Z5<=0,"Low Profit",IF(Z5>=50,"HighProfit","Medium Profit")) | AE5: =TEXT(B5,"mmmm")
A6: ORD-00054 | B6: 45661 | C6: 2025 | D6: 1 | E6: Saudi Arabia | F6: Jeddah | G6: Google Ads | H6: Retargeting | I6: P009 | J6: Car Vacuum Cleaner | K6: Automotive | L6: Dongguan Auto Tools | M6: 41.33 | N6: 15.02 | O6: 7.07 | P6: 0.03 | Q6: 27.25 | R6: 3 | S6: =IF(AC6="Cancelled",0,M6*R6) | T6: =IF(AC6="Cancelled",0,N6*R6) | U6: =IF(AC6="Cancelled",0,O6*R6) | V6: =IF(AC6="Cancelled",0,ROUND(P6*S6,2)) | W6: No | X6: 0 | Y6: =IF(AC6="Cancelled",0,T6+U6+V6+Q6+X6) | Z6: =IF(AC6="Cancelled",-Q6,S6-Y6) | AA6: =IF(OR(AC6="Cancelled",S6=0),0,Z6/S6) | AB6: =IFERROR(IF(Q6=0,0,S6/Q6),0) | AC6: Delivered | AD6: =IF(Z6<=0,"Low Profit",IF(Z6>=50,"HighProfit","Medium Profit")) | AE6: =TEXT(B6,"mmmm")
A7: ORD-00386 | B7: 45661 | C7: 2025 | D7: 1 | E7: Qatar | F7: Doha | G7: Email | H7: Retargeting | I7: P006 | J7: Posture Corrector | K7: Fitness | L7: Hangzhou Health Gear | M7: 36.04 | N7: 8.56 | O7: 3.75 | P7: 0.03 | Q7: 8.57 | R7: 1 | S7: =IF(AC7="Cancelled",0,M7*R7) | T7: =IF(AC7="Cancelled",0,N7*R7) | U7: =IF(AC7="Cancelled",0,O7*R7) | V7: =IF(AC7="Cancelled",0,ROUND(P7*S7,2)) | W7: No | X7: 0 | Y7: =IF(AC7="Cancelled",0,T7+U7+V7+Q7+X7) | Z7: =IF(AC7="Cancelled",-Q7,S7-Y7) | AA7: =IF(OR(AC7="Cancelled",S7=0),0,Z7/S7) | AB7: =IFERROR(IF(Q7=0,0,S7/Q7),0) | AC7: Delivered | AD7: =IF(Z7<=0,"Low Profit",IF(Z7>=50,"HighProfit","Medium Profit")) | AE7: =TEXT(B7,"mmmm")
A8: ORD-00040 | B8: 45664 | C8: 2025 | D8: 1 | E8: UAE | F8: Abu Dhabi | G8: Email | H8: Summer Sale | I8: P003 | J8: LED Strip Lights | K8: Home Decor | L8: Yiwu Lighting Factory | M8: 26.71 | N8: 6.12 | O8: 3.4 | P8: 0.03 | Q8: 6.87 | R8: 1 | S8: =IF(AC8="Cancelled",0,M8*R8) | T8: =IF(AC8="Cancelled",0,N8*R8) | U8: =IF(AC8="Cancelled",0,O8*R8) | V8: =IF(AC8="Cancelled",0,ROUND(P8*S8,2)) | W8: No | X8: 0 | Y8: =IF(AC8="Cancelled",0,T8+U8+V8+Q8+X8) | Z8: =IF(AC8="Cancelled",-Q8,S8-Y8) | AA8: =IF(OR(AC8="Cancelled",S8=0),0,Z8/S8) | AB8: =IFERROR(IF(Q8=0,0,S8/Q8),0) | AC8: Delivered | AD8: =IF(Z8<=0,"Low Profit",IF(Z8>=50,"HighProfit","Medium Profit")) | AE8: =TEXT(B8,"mmmm")
A9: ORD-00203 | B9: 45664 | C9: 2025 | D9: 1 | E9: UAE | F9: Sharjah | G9: TikTok Ads | H9: Summer Sale | I9: P006 | J9: Posture Corrector | K9: Fitness | L9: Hangzhou Health Gear | M9: 33.08 | N9: 9.71 | O9: 3.77 | P9: 0.03 | Q9: 3.96 | R9: 2 | S9: =IF(AC9="Cancelled",0,M9*R9) | T9: =IF(AC9="Cancelled",0,N9*R9) | U9: =IF(AC9="Cancelled",0,O9*R9) | V9: =IF(AC9="Cancelled",0,ROUND(P9*S9,2)) | W9: No | X9: 0 | Y9: =IF(AC9="Cancelled",0,T9+U9+V9+Q9+X9) | Z9: =IF(AC9="Cancelled",-Q9,S9-Y9) | AA9: =IF(OR(AC9="Cancelled",S9=0),0,Z9/S9) | AB9: =IFERROR(IF(Q9=0,0,S9/Q9),0) | AC9: Delivered | AD9: =IF(Z9<=0,"Low Profit",IF(Z9>=50,"HighProfit","Medium Profit")) | AE9: =TEXT(B9,"mmmm")
A10: ORD-00038 | B10: 45665 | C10: 2025 | D10: 1 | E10: UAE | F10: Sharjah | G10: Google Ads | H10: Summer Sale | I10: P007 | J10: Pet Grooming Glove | K10: Pets | L10: Yiwu Pet Products | M10: 20.42 | N10: 3.35 | O10: 2.49 | P10: 0.03 | Q10: 16.08 | R10: 3 | S10: =IF(AC10="Cancelled",0,M10*R10) | T10: =IF(AC10="Cancelled",0,N10*R10) | U10: =IF(AC10="Cancelled",0,O10*R10) | V10: =IF(AC10="Cancelled",0,ROUND(P10*S10,2)) | W10: No | X10: 0 | Y10: =IF(AC10="Cancelled",0,T10+U10+V10+Q10+X10) | Z10: =IF(AC10="Cancelled",-Q10,S10-Y10) | AA10: =IF(OR(AC10="Cancelled",S10=0),0,Z10/S10) | AB10: =IFERROR(IF(Q10=0,0,S10/Q10),0) | AC10: Delivered | AD10: =IF(Z10<=0,"Low Profit",IF(Z10>=50,"HighProfit","Medium Profit")) | AE10: =TEXT(B10,"mmmm")
A11: ORD-00401 | B11: 45666 | C11: 2025 | D11: 1 | E11: UAE | F11: Dubai | G11: Google Ads | H11: Launch Test | I11: P008 | J11: Portable Blender | K11: Kitchen | L11: Foshan Appliances | M11: 53.18 | N11: 16.82 | O11: 5.87 | P11: 0.03 | Q11: 5.9 | R11: 1 | S11: =IF(AC11="Cancelled",0,M11*R11) | T11: =IF(AC11="Cancelled",0,N11*R11) | U11: =IF(AC11="Cancelled",0,O11*R11) | V11: =IF(AC11="Cancelled",0,ROUND(P11*S11,2)) | W11: No | X11: 0 | Y11: =IF(AC11="Cancelled",0,T11+U11+V11+Q11+X11) | Z11: =IF(AC11="Cancelled",-Q11,S11-Y11) | AA11: =IF(OR(AC11="Cancelled",S11=0),0,Z11/S11) | AB11: =IFERROR(IF(Q11=0,0,S11/Q11),0) | AC11: Delivered | AD11: =IF(Z11<=0,"Low Profit",IF(Z11>=50,"HighProfit","Medium Profit")) | AE11: =TEXT(B11,"mmmm")
A12: ORD-00451 | B12: 45667 | C12: 2025 | D12: 1 | E12: UAE | F12: Dubai | G12: TikTok Ads | H12: Launch Test | I12: P003 | J12: LED Strip Lights | K12: Home Decor | L12: Yiwu Lighting Factory | M12: 24.36 | N12: 6.05 | O12: 3.32 | P12: 0.03 | Q12: 3.24 | R12: 1 | S12: =IF(AC12="Cancelled",0,M12*R12) | T12: =IF(AC12="Cancelled",0,N12*R12) | U12: =IF(AC12="Cancelled",0,O12*R12) | V12: =IF(AC12="Cancelled",0,ROUND(P12*S12,2)) | W12: No | X12: 0 | Y12: =IF(AC12="Cancelled",0,T12+U12+V12+Q12+X12) | Z12: =IF(AC12="Cancelled",-Q12,S12-Y12) | AA12: =IF(OR(AC12="Cancelled",S12=0),0,Z12/S12) | AB12: =IFERROR(IF(Q12=0,0,S12/Q12),0) | AC12: Delivered | AD12: =IF(Z12<=0,"Low Profit",IF(Z12>=50,"HighProfit","Medium Profit")) | AE12: =TEXT(B12,"mmmm")
A13: ORD-00309 | B13: 45668 | C13: 2025 | D13: 1 | E13: Oman | F13: Muscat | G13: TikTok Ads | H13: Launch Test | I13: P009 | J13: Car Vacuum Cleaner | K13: Automotive | L13: Dongguan Auto Tools | M13: 45.62 | N13: 13.94 | O13: 7.25 | P13: 0.03 | Q13: 4.62 | R13: 2 | S13: =IF(AC13="Cancelled",0,M13*R13) | T13: =IF(AC13="Cancelled",0,N13*R13) | U13: =IF(AC13="Cancelled",0,O13*R13) | V13: =IF(AC13="Cancelled",0,ROUND(P13*S13,2)) | W13: No | X13: 0 | Y13: =IF(AC13="Cancelled",0,T13+U13+V13+Q13+X13) | Z13: =IF(AC13="Cancelled",-Q13,S13-Y13) | AA13: =IF(OR(AC13="Cancelled",S13=0),0,Z13/S13) | AB13: =IFERROR(IF(Q13=0,0,S13/Q13),0) | AC13: Delivered | AD13: =IF(Z13<=0,"Low Profit",IF(Z13>=50,"HighProfit","Medium Profit")) | AE13: =TEXT(B13,"mmmm")
... A501: ORD-00448 | B501: 46141 | C501: 2026 | D501: 4 | E501: Saudi Arabia | F501: Jeddah | G501: Google Ads | H501: Retargeting | I501: P004 | J501: Beauty Tool | K501: Beauty | L501: Ningbo Beauty Supply | M501: 30.3 | N501: 6.84 | O501: 4.26 | P501: 0.03 | Q501: 7.6 | R501: 2 | S501: =IF(AC501="Cancelled",0,M501*R501) | T501: =IF(AC501="Cancelled",0,N501*R501) | U501: =IF(AC501="Cancelled",0,O501*R501) | V501: =IF(AC501="Cancelled",0,ROUND(P501*S501,2)) | W501: No | X501: 0 | Y501: =IF(AC501="Cancelled",0,T501+U501+V501+Q501+X501) | Z501: =IF(AC501="Cancelled",-Q501,S501-Y501) | AA501: =IF(OR(AC501="Cancelled",S501=0),0,Z501/S501) | AB501: =IFERROR(IF(Q501=0,0,S501/Q501),0) | AC501: Cancelled | AD501: =IF(Z501<=0,"Low Profit",IF(Z501>=50,"HighProfit","Medium Profit")) | AE501: =TEXT(B501,"mmmm")

Sheet Executive Dashboard
B2: Dashboard — Live Product Profitability
B5: Revenue | D5: Net Profit | F5: ROAS | H5: Score
B6: ='Profit Calculator'!C10 | D6: ='Profit Calculator'!C26 | F6: ='Profit Calculator'!C34 | H6: ='Profit Calculator'!H11
B9: Executive Summary
B10: Product Verdict | C10: ='Profit Calculator'!H12
B11: Ad Safety | C11: ='Profit Calculator'!H13
B12: Break-even ROAS | C12: ='Profit Calculator'!C40
B13: Break-even CAC | C13: ='Profit Calculator'!C41
B14: Profit Margin | C14: ='Profit Calculator'!C27
B15: LTV:CAC | C15: ='Profit Calculator'!C36
B18: Metric | C18: Value
B19: Revenue | C19: ='Profit Calculator'!C10
B20: Total Costs | C20: ='Profit Calculator'!C21
B21: Net Profit | C21: ='Profit Calculator'!C26
B22: Ad Spend | C22: ='Profit Calculator'!C17
